LICENSE
README.md
zdppy_password/__init__.py
zdppy_password/aes.py
zdppy_password/b64.py
zdppy_password/ecc.py
zdppy_password/hash.py
zdppy_password/libs/__init__.py
zdppy_password/libs/rsa/__init__.py
zdppy_password/libs/rsa/_compat.py
zdppy_password/libs/rsa/asn1.py
zdppy_password/libs/rsa/cli.py
zdppy_password/libs/rsa/common.py
zdppy_password/libs/rsa/core.py
zdppy_password/libs/rsa/key.py
zdppy_password/libs/rsa/parallel.py
zdppy_password/libs/rsa/pem.py
zdppy_password/libs/rsa/pkcs1.py
zdppy_password/libs/rsa/pkcs1_v2.py
zdppy_password/libs/rsa/prime.py
zdppy_password/libs/rsa/randnum.py
zdppy_password/libs/rsa/transform.py
zdppy_password/libs/rsa/util.py
zdppy_password/rsa.py
zdppy_password/zdppy_password.py
zdppy_password-0.1.0.dist-info/LICENSE
zdppy_password-0.1.0.dist-info/WHEEL
zdppy_password-0.1.0.dist-info/METADATA
zdppy_password-0.1.0.dist-info/RECORD
