Metadata-Version: 2.1
Name: zdppy-password
Version: 0.1.0
Summary: Python用于处理数据和文件加密解密的库
Home-page: https://github.com/zhangdapeng520/zdppy_password
License: MIT
Keywords: poetry,zhangdapeng,zhangdapeng520,password,zdppy_password,zdppy
Author: zhangdapeng520
Author-email: pygosuperman@outlook.com
Requires-Python: >=3.9,<4.0
Classifier: Development Status :: 3 - Alpha
Classifier: Environment :: Console
Classifier: Intended Audience :: Developers
Classifier: License :: OSI Approved :: MIT License
Classifier: Operating System :: OS Independent
Classifier: Programming Language :: Python :: 3
Classifier: Programming Language :: Python :: 3 :: Only
Classifier: Programming Language :: Python :: 3.10
Classifier: Programming Language :: Python :: 3.9
Requires-Dist: pycryptodome (>=3.14.1,<4.0.0)
Requires-Dist: rsa (>=4.8,<5.0)
Requires-Dist: tinyec (>=0.4.0,<0.5.0)
Requires-Dist: zdppy-log (>=0.1.7,<0.2.0)
Project-URL: Repository, https://github.com/zhangdapeng520/zdppy_password
